{
    "SECRET_KEY": "",
    "KAKAO_REST_API_KEY": "",
    "BASE_URL": "",
    "KAKAO_CALLBACK_URI": "",
    "GOOGLE_CLIENT_ID": "",
    "GOOGLE_CLIENT_SECRET": "",
    "DEBUG": false,
    "AWS_ACCESS_KEY_ID": "",
    "AWS_SECRET_ACCESS_KEY": "",
    "AWS_STORAGE_BUCKET_NAME": "",
    "DEFAULT_FILE_STORAGE": "",
    "AWS_S3_REGION_NAME": "",
    "AWS_S3_SIGNATURE_VERSION": "",
    "POSTGRES_DB": "",
    "POSTGRES_USER": "",
    "POSTGRES_PASSWORD": "",
    "MONGODB_DB": "",
    "MONGODB_USERNAME": "",
    "MONGODB_PASSWORD": ""
}